jixn_utils/GetConfig.py
jixn_utils/JudgeFile.py
jixn_utils/__init__.py
jixn_utils/dbmysql.py
jixn_utils/gen_guid.py
jixn_utils/jixn_parser.py
jixn_utils/jixn_parser_嵌套类型.py
jixn_utils/jixn_utils.py
jixn_utils/sendnews.py
jixn_utils-0.0.3.dist-info/LICENSE.txt
jixn_utils-0.0.3.dist-info/METADATA
jixn_utils-0.0.3.dist-info/WHEEL
jixn_utils-0.0.3.dist-info/top_level.txt
jixn_utils-0.0.3.dist-info/RECORD
